setalgebra/__init__.py
setalgebra/__main__.py
setalgebra/exceptions.py
setalgebra/version.py
setalgebra_files-1.0.0.dist-info/LICENSE
setalgebra_files-1.0.0.dist-info/METADATA
setalgebra_files-1.0.0.dist-info/WHEEL
setalgebra_files-1.0.0.dist-info/entry_points.txt
setalgebra_files-1.0.0.dist-info/top_level.txt
setalgebra_files-1.0.0.dist-info/RECORD
