Metadata-Version: 2.1
Name: setalgebra-files
Version: 1.0.0
Summary: Arbitrary set calculations using the shunting yard algorithm
Home-page: https://gitlab.com/jfriis/setalgebra
Author: Jens Friis-Nielsen
Author-email: jensfriisnielsen@gmail.com
License: GNU General Public License v3 or later (GPLv3+)
Project-URL: Bug Tracker, https://gitlab.com/jfriis/setalgebra/-/issues
Platform: UNKNOWN
Classifier: Programming Language :: Python :: 3
Classifier: License :: OSI Approved :: GNU General Public License v3 or later (GPLv3+)
Classifier: Operating System :: OS Independent
Requires-Python: >=3.7
License-File: LICENSE
